sphinx_run-0.2.2.dist-info/licenses/LICENSE.rst
sphinxrun/__init__.py
sphinxrun/directive.py
sphinxrun/runner.py
sphinx_run-0.2.2.dist-info/METADATA
sphinx_run-0.2.2.dist-info/WHEEL
sphinx_run-0.2.2.dist-info/top_level.txt
sphinx_run-0.2.2.dist-info/RECORD
