Metadata-Version: 2.4
Name: sphinx-run
Version: 0.2.2
Summary: Dynamically generated content for sphinx documentations
License-Expression: BSD-2-Clause
Classifier: Framework :: Sphinx
Classifier: Framework :: Sphinx :: Extension
Classifier: Intended Audience :: Developers
Classifier: Programming Language :: Python
Classifier: Programming Language :: Python :: 3 :: Only
Classifier: Programming Language :: Python :: 3.10
Classifier: Programming Language :: Python :: 3.11
Classifier: Programming Language :: Python :: 3.12
Classifier: Programming Language :: Python :: 3.13
Classifier: Topic :: Documentation
Classifier: Topic :: Documentation :: Sphinx
Requires-Python: >=3.10
License-File: LICENSE.rst
Requires-Dist: sphinx>=8
Provides-Extra: dev
Requires-Dist: esbonio; extra == "dev"
Requires-Dist: pyproject-fmt; extra == "dev"
Requires-Dist: ruff; extra == "dev"
Provides-Extra: doc
Requires-Dist: furo; extra == "doc"
Dynamic: license-file
